jsonpath_sleuth-0.1.2.dist-info/METADATA
jsonpath_sleuth-0.1.2.dist-info/WHEEL
jsonpath_sleuth-0.1.2.dist-info/licenses/LICENSE
jsonpath_sleuth.pyi
jsonpath_sleuth/__init__.py
jsonpath_sleuth/__init__.pyi
jsonpath_sleuth/jsonpath_sleuth.abi3.so
jsonpath_sleuth/py.typed
jsonpath_sleuth-0.1.2.dist-info/RECORD
