Metadata-Version: 2.4
Name: jsonpath-sleuth
Version: 0.1.2
Classifier: Programming Language :: Python
Classifier: Programming Language :: Python :: 3
Classifier: Programming Language :: Python :: 3 :: Only
Classifier: Programming Language :: Python :: 3.8
Classifier: Programming Language :: Python :: 3.9
Classifier: Programming Language :: Python :: 3.10
Classifier: Programming Language :: Python :: 3.11
Classifier: Programming Language :: Python :: 3.12
Classifier: Programming Language :: Python :: 3.13
Classifier: Programming Language :: Rust
Classifier: Operating System :: OS Independent
Classifier: License :: OSI Approved :: MIT License
Requires-Dist: pytest ; extra == 'dev'
Requires-Dist: maturin>=1.6,<2 ; extra == 'dev'
Provides-Extra: dev
License-File: LICENSE
Summary: Python bindings for fast JSONPath resolve and value-to-path search implemented in Rust
Author: Your Name
License: MIT
Requires-Python: >=3.8
